multimodal_factory/__init__.py
multimodal_factory/adapters.py
multimodal_factory/config.py
multimodal_factory/core.py
multimodal_factory/factory.py
multimodal_factory/utils.py
mm_factory-0.1.1.dist-info/METADATA
mm_factory-0.1.1.dist-info/WHEEL
mm_factory-0.1.1.dist-info/top_level.txt
mm_factory-0.1.1.dist-info/RECORD
