Metadata-Version: 2.4
Name: mm_factory
Version: 0.1.1
Summary: VLM factory
Author-email: Your Name <Karouswissem@gmail.com>
Requires-Python: >=3.10
Dynamic: requires-python
